[
    {
        "model": "produtos",

        "documents" : [
            {
             "nome":"Forro de cama A",
             "descricao":"toalha fofa",
             "valor":"110",
             "valor_total":"90",
             "fotos":["foto1","foto2","foto3"]
            },
            {
             "nome":"Forro de cama B",
             "descricao":"toalha fofa",
             "valor":"110",
             "valor_total":"90",
             "fotos":["foto1","foto2","foto3"]
            },
            {
             "nome":"Forro de cama C",
             "descricao":"toalha fofa",
             "valor":"110",
             "valor_total":"90",
             "fotos":["foto1","foto2","foto3"]
            },
            {
             "nome":"Forro de cama D",
             "descricao":"toalha fofa",
             "valor":"110",
             "valor_total":"90",
             "fotos":["foto1","foto2","foto3"]
            },
            {
              "nome":"Forro de cama E","descricao":"toalha fofa",
              "valor":"110",
              "valor_total":"90",
              "fotos":["foto1","foto2","foto3"]
            },
            {
              "nome":"Forro de cama F","descricao":"toalha fofa",
              "valor":"110",
              "valor_total":"90",
              "fotos":["foto1","foto2","foto3"]
            },
            {
              "nome":"Forro de cama G","descricao":"toalha fofa",
              "valor":"110",
              "valor_total":"90",
              "fotos":["foto1","foto2","foto3"]
            },
            {
              "nome":"Forro de cama H","descricao":"toalha fofa",
              "valor":"110",
              "valor_total":"90",
              "fotos":["foto1","foto2","foto3"]
            },
            {
              "nome":"Forro de cama I",
              "descricao":"toalha fofa",
              "valor":"110",
              "valor_total":"90",
              "fotos":["foto1","foto2","foto3"]
            },
            {
              "nome":"Toalha A","descricao":"toalha fofa",
              "valor":"110",
              "valor_total":"90",
              "fotos":["foto1","foto2","foto3"]
            },
            {
              "nome":"Toalha B","descricao":"toalha fofa",
              "valor":"110",
              "valor_total":"90",
              "fotos":["foto1","foto2","foto3"]
            },
            {
              "nome":"Toalha C","descricao":"toalha fofa",
              "valor":"110",
              "valor_total":"90",
              "fotos":["foto1","foto2","foto3"]
            },
            {
              "nome":"Toalha D","descricao":"toalha fofa",
              "valor":"110",
              "valor_total":"90",
              "fotos":["foto1","foto2","foto3"]
            },
            {
              "nome":"Toalha E","descricao":"toalha fofa",
              "valor":"110",
              "valor_total":"90",
              "fotos":["foto1","foto2","foto3"]
            },
            {
              "nome":"Toalha F","descricao":"toalha fofa",
              "valor":"110",
              "valor_total":"90",
              "fotos":["foto1","foto2","foto3"]
            },
            {
              "nome":"Toalha G","descricao":"toalha fofa",
              "valor":"110",
              "valor_total":"90",
              "fotos":["foto1","foto2","foto3"]
            },
            {
              "nome":"Toalha H","descricao":"toalha fofa",
              "valor":"110",
              "valor_total":"90",
              "fotos":["foto1","foto2","foto3"]
            },
            {
              "nome":"Toalha I","descricao":"toalha fofa",
              "valor":"110",
              "valor_total":"90",
              "fotos":["foto1","foto2","foto3"]
            }
        ]
    }
]